islabtech_upw_sensor_v1_mock_api/__init__.py
islabtech_upw_sensor_v1_mock_api/__main__.py
islabtech_upw_sensor_v1_mock_api/tests/test_modbus.py
islabtech_upw_sensor_v1_mock_api/tests/test_units.py
islabtech_upw_sensor_v1_mock_api-0.1.6.dist-info/METADATA
islabtech_upw_sensor_v1_mock_api-0.1.6.dist-info/WHEEL
islabtech_upw_sensor_v1_mock_api-0.1.6.dist-info/RECORD
