Metadata-Version: 2.4
Name: islabtech_upw_sensor_v1_mock_api
Version: 0.1.6
Summary: Mock API simulating the Rest+Modbus/TCP API of the ISLabTech UPW sensor
Project-URL: Bug Tracker, https://gitlab.com/islabtech/upw-sensor/api
Author-email: Ilka Schulz <ilka@islabtech.com>
Classifier: Natural Language :: English
Classifier: Operating System :: OS Independent
Classifier: Programming Language :: Python :: 3.7
Requires-Python: >=3.7
Requires-Dist: apscheduler~=3.0
Requires-Dist: flask-sock<1,>=0.7
Requires-Dist: flask~=3.0
Requires-Dist: pymodbus<=3.9.2,>=3.5.4
Requires-Dist: pymodbustcp<1,>=0.3
Requires-Dist: requests~=2.0
